nonebot_plugin_miragetank-0.2.2.dist-info/METADATA
nonebot_plugin_miragetank-0.2.2.dist-info/WHEEL
nonebot_plugin_miragetank-0.2.2.dist-info/entry_points.txt
nonebot_plugin_miragetank-0.2.2.dist-info/licenses/LICENSE
nonebot_plugin_miragetank/__init__.py
nonebot_plugin_miragetank/data_source.py
nonebot_plugin_miragetank/depends.py
nonebot_plugin_miragetank-0.2.2.dist-info/RECORD
