Metadata-Version: 2.1
Name: nonebot-plugin-miragetank
Version: 0.2.2
Summary: 生成幻影坦克图，在不同背景下显示不同图片
Author-Email: 1umine <a1628420979@163.com>
License: GPL
Requires-Python: >=3.10
Requires-Dist: numpy<2.0,>=1.24
Requires-Dist: Pillow>=9.0.0
Requires-Dist: nonebot2<3.0,>=2.0
Requires-Dist: httpx>=0.27.0
Requires-Dist: nonebot-plugin-alconna>=0.42.4
Requires-Dist: nonebot-plugin-waiter>=0.6.2
